[
    {
        "name": "Rodney McGruder",
        "nameAbv": "R. McGruder",
        "min": "36",
        "pts": "10",
        "fgmA": "4 - 13",
        "ftmA": "0 - 0",
        "threepmA": "2 - 8",
        "reb": "6",
        "ast": "3",
        "stl": "1",
        "to": "0",
        "pf": "1"
    },
    {
        "name": "Hassan Whiteside",
        "nameAbv": "H. Whiteside",
        "min": "34",
        "pts": "23",
        "fgmA": "10 - 12",
        "ftmA": "3 - 6",
        "threepmA": "0 - 0",
        "reb": "16",
        "ast": "0",
        "stl": "0",
        "to": "1",
        "pf": "3"
    },
    {
        "name": "Goran Dragic",
        "nameAbv": "G. Dragic",
        "min": "34",
        "pts": "16",
        "fgmA": "7 - 13",
        "ftmA": "2 - 3",
        "threepmA": "0 - 2",
        "reb": "4",
        "ast": "7",
        "stl": "2",
        "to": "0",
        "pf": "5"
    },
    {
        "name": "Wayne Ellington",
        "nameAbv": "W. Ellington",
        "min": "28",
        "pts": "17",
        "fgmA": "6 - 11",
        "ftmA": "0 - 0",
        "threepmA": "5 - 8",
        "reb": "2",
        "ast": "1",
        "stl": "0",
        "to": "0",
        "pf": "1"
    },
    {
        "name": "Luke Babbitt",
        "nameAbv": "L. Babbitt",
        "min": "20",
        "pts": "0",
        "fgmA": "0 - 6",
        "ftmA": "0 - 0",
        "threepmA": "0 - 5",
        "reb": "2",
        "ast": "1",
        "stl": "0",
        "to": "0",
        "pf": "1"
    },
    {
        "name": "James Johnson",
        "nameAbv": "J. Johnson",
        "min": "30",
        "pts": "20",
        "fgmA": "7 - 12",
        "ftmA": "4 - 5",
        "threepmA": "2 - 5",
        "reb": "4",
        "ast": "4",
        "stl": "2",
        "to": "2",
        "pf": "3"
    },
    {
        "name": "Tyler Johnson",
        "nameAbv": "T. Johnson",
        "min": "27",
        "pts": "8",
        "fgmA": "3 - 11",
        "ftmA": "2 - 2",
        "threepmA": "0 - 2",
        "reb": "4",
        "ast": "6",
        "stl": "0",
        "to": "2",
        "pf": "0"
    },
    {
        "name": "Okaro White",
        "nameAbv": "O. White",
        "min": "17",
        "pts": "7",
        "fgmA": "2 - 3",
        "ftmA": "2 - 2",
        "threepmA": "1 - 2",
        "reb": "5",
        "ast": "1",
        "stl": "0",
        "to": "0",
        "pf": "0"
    },
    {
        "name": "Willie Reed",
        "nameAbv": "W. Reed",
        "min": "14",
        "pts": "5",
        "fgmA": "2 - 5",
        "ftmA": "0 - 0",
        "threepmA": "1 - 1",
        "reb": "5",
        "ast": "0",
        "stl": "0",
        "to": "0",
        "pf": "1"
    },
    {
        "name": "Marcus Georges-Hunt",
        "nameAbv": "M. Georges-Hunt",
        "min": "COACH'S DECISION",
        "pts": "",
        "fgmA": "",
        "ftmA": "",
        "threepmA": "",
        "reb": "",
        "ast": "",
        "stl": "",
        "to": "",
        "pf": ""
    },
    {
        "name": "Udonis Haslem",
        "nameAbv": "U. Haslem",
        "min": "COACH'S DECISION",
        "pts": "",
        "fgmA": "",
        "ftmA": "",
        "threepmA": "",
        "reb": "",
        "ast": "",
        "stl": "",
        "to": "",
        "pf": ""
    },
    {
        "name": "Josh Richardson",
        "nameAbv": "J. Richardson",
        "min": "LEFT FOOT SPRAIN",
        "pts": "",
        "fgmA": "",
        "ftmA": "",
        "threepmA": "",
        "reb": "",
        "ast": "",
        "stl": "",
        "to": "",
        "pf": ""
    },
    {
        "name": "Dion Waiters",
        "nameAbv": "D. Waiters",
        "min": "LEFT ANKLE SPRAIN",
        "pts": "",
        "fgmA": "",
        "ftmA": "",
        "threepmA": "",
        "reb": "",
        "ast": "",
        "stl": "",
        "to": "",
        "pf": ""
    },
    {
        "name": "Giannis Antetokounmpo",
        "nameAbv": "G. Antetokounmpo",
        "min": "36",
        "pts": "22",
        "fgmA": "9 - 15",
        "ftmA": "2 - 2",
        "threepmA": "2 - 3",
        "reb": "8",
        "ast": "1",
        "stl": "2",
        "to": "1",
        "pf": "4"
    },
    {
        "name": "Tony Snell",
        "nameAbv": "T. Snell",
        "min": "34",
        "pts": "6",
        "fgmA": "2 - 6",
        "ftmA": "0 - 0",
        "threepmA": "2 - 4",
        "reb": "2",
        "ast": "1",
        "stl": "0",
        "to": "0",
        "pf": "1"
    },
    {
        "name": "John Henson",
        "nameAbv": "J. Henson",
        "min": "26",
        "pts": "5",
        "fgmA": "1 - 3",
        "ftmA": "3 - 5",
        "threepmA": "0 - 0",
        "reb": "5",
        "ast": "0",
        "stl": "3",
        "to": "2",
        "pf": "2"
    },
    {
        "name": "Jabari Parker",
        "nameAbv": "J. Parker",
        "min": "20",
        "pts": "14",
        "fgmA": "6 - 11",
        "ftmA": "2 - 3",
        "threepmA": "0 - 1",
        "reb": "1",
        "ast": "2",
        "stl": "1",
        "to": "0",
        "pf": "2"
    },
    {
        "name": "Matthew Dellavedova",
        "nameAbv": "M. Dellavedova",
        "min": "15",
        "pts": "5",
        "fgmA": "2 - 6",
        "ftmA": "0 - 0",
        "threepmA": "1 - 2",
        "reb": "1",
        "ast": "1",
        "stl": "0",
        "to": "0",
        "pf": "0"
    },
    {
        "name": "Malcolm Brogdon",
        "nameAbv": "M. Brogdon",
        "min": "33",
        "pts": "6",
        "fgmA": "2 - 7",
        "ftmA": "2 - 4",
        "threepmA": "0 - 1",
        "reb": "2",
        "ast": "6",
        "stl": "3",
        "to": "0",
        "pf": "1"
    },
    {
        "name": "Greg Monroe",
        "nameAbv": "G. Monroe",
        "min": "22",
        "pts": "6",
        "fgmA": "2 - 5",
        "ftmA": "2 - 3",
        "threepmA": "0 - 0",
        "reb": "7",
        "ast": "2",
        "stl": "0",
        "to": "0",
        "pf": "0"
    },
    {
        "name": "Khris Middleton",
        "nameAbv": "K. Middleton",
        "min": "15",
        "pts": "5",
        "fgmA": "2 - 5",
        "ftmA": "1 - 2",
        "threepmA": "0 - 1",
        "reb": "2",
        "ast": "2",
        "stl": "0",
        "to": "1",
        "pf": "0"
    },
    {
        "name": "Jason Terry",
        "nameAbv": "J. Terry",
        "min": "14",
        "pts": "5",
        "fgmA": "2 - 2",
        "ftmA": "1 - 2",
        "threepmA": "0 - 0",
        "reb": "1",
        "ast": "3",
        "stl": "1",
        "to": "0",
        "pf": "0"
    },
    {
        "name": "Mirza Teletovic",
        "nameAbv": "M. Teletovic",
        "min": "13",
        "pts": "3",
        "fgmA": "1 - 5",
        "ftmA": "0 - 0",
        "threepmA": "1 - 3",
        "reb": "2",
        "ast": "0",
        "stl": "0",
        "to": "0",
        "pf": "0"
    },
    {
        "name": "Michael Beasley",
        "nameAbv": "M. Beasley",
        "min": "12",
        "pts": "11",
        "fgmA": "4 - 6",
        "ftmA": "3 - 7",
        "threepmA": "0 - 0",
        "reb": "3",
        "ast": "0",
        "stl": "0",
        "to": "0",
        "pf": "2"
    },
    {
        "name": "Thon Maker",
        "nameAbv": "T. Maker",
        "min": "COACH'S DECISION",
        "pts": "",
        "fgmA": "",
        "ftmA": "",
        "threepmA": "",
        "reb": "",
        "ast": "",
        "stl": "",
        "to": "",
        "pf": ""
    },
    {
        "name": "Rashad Vaughn",
        "nameAbv": "R. Vaughn",
        "min": "COACH'S DECISION",
        "pts": "",
        "fgmA": "",
        "ftmA": "",
        "threepmA": "",
        "reb": "",
        "ast": "",
        "stl": "",
        "to": "",
        "pf": ""
    }
]